workflow_server/__init__.py
workflow_server/api/__init__.py
workflow_server/api/auth_middleware.py
workflow_server/api/healthz_view.py
workflow_server/api/status_view.py
workflow_server/api/tests/__init__.py
workflow_server/api/tests/test_emit_async_error_events.py
workflow_server/api/tests/test_input_display_mapping.py
workflow_server/api/tests/test_workflow_view.py
workflow_server/api/tests/test_workflow_view_async_exec.py
workflow_server/api/tests/test_workflow_view_stream_workflow_route.py
workflow_server/api/tests/test_workflow_view_type_check.py
workflow_server/api/workflow_view.py
workflow_server/code_exec_runner.py
workflow_server/config.py
workflow_server/core/__init__.py
workflow_server/core/cancel_workflow.py
workflow_server/core/events.py
workflow_server/core/executor.py
workflow_server/core/type_check.py
workflow_server/core/type_checker/__init__.py
workflow_server/core/type_checker/base.py
workflow_server/core/type_checker/mypy.py
workflow_server/core/type_checker/serialization.mypy.ini
workflow_server/core/type_checker/zuban.py
workflow_server/core/utils.py
workflow_server/core/workflow_executor_context.py
workflow_server/logging_config.py
workflow_server/server.py
workflow_server/start.py
workflow_server/utils/__init__.py
workflow_server/utils/exit_handler.py
workflow_server/utils/log_proxy.py
workflow_server/utils/oom_killer.py
workflow_server/utils/sentry.py
workflow_server/utils/system_utils.py
workflow_server/utils/tests/__init__.py
workflow_server/utils/tests/test_sentry_integration.py
workflow_server/utils/tests/test_system_utils.py
workflow_server/utils/tests/test_utils.py
workflow_server/utils/utils.py
vellum_workflow_server-1.14.1.post1.dist-info/METADATA
vellum_workflow_server-1.14.1.post1.dist-info/WHEEL
vellum_workflow_server-1.14.1.post1.dist-info/entry_points.txt
vellum_workflow_server-1.14.1.post1.dist-info/RECORD
