Metadata-Version: 2.1
Name: vellum-workflow-server
Version: 1.14.1.post1
Summary: 
License: AGPL
Requires-Python: >=3.9.0,<4
Classifier: Intended Audience :: Developers
Classifier: License :: OSI Approved :: MIT License
Classifier: License :: Other/Proprietary License
Classifier: Operating System :: MacOS
Classifier: Operating System :: Microsoft :: Windows
Classifier: Operating System :: OS Independent
Classifier: Operating System :: POSIX
Classifier: Operating System :: POSIX :: Linux
Classifier: Programming Language :: Python
Classifier: Programming Language :: Python :: 3
Classifier: Programming Language :: Python :: 3.9
Classifier: Programming Language :: Python :: 3.10
Classifier: Programming Language :: Python :: 3.11
Classifier: Programming Language :: Python :: 3.12
Classifier: Programming Language :: Python :: 3.13
Classifier: Topic :: Software Development :: Libraries :: Python Modules
Classifier: Typing :: Typed
Requires-Dist: flask (==2.3.3)
Requires-Dist: gunicorn (==23.0.0)
Requires-Dist: orderly-set (==5.2.2)
Requires-Dist: orjson (==3.11.4)
Requires-Dist: packaging
Requires-Dist: pydantic (>2)
Requires-Dist: pyjwt[crypto] (==2.10.0)
Requires-Dist: python-dotenv (==1.2.1)
Requires-Dist: requests (>=2.31.0)
Requires-Dist: retrying (==1.3.4)
Requires-Dist: sentry-sdk[flask] (==2.20.0)
Requires-Dist: vellum-ai[mypy,zuban] (==1.14.1)
Requires-Dist: werkzeug (>2)
